[{"line":2,"elements":[{"line":4,"name":"","description":"","type":"background","keyword":"Background","steps":[{"name":"url baseUrl","result":{"duration":157300,"status":"passed"},"match":{"location":"karate","arguments":[]},"keyword":"*","line":5},{"name":"configure headers = { Accept: 'application\/json' }","result":{"duration":171400,"status":"passed"},"match":{"location":"karate","arguments":[]},"comments":["# configure headers garantiza que Accept: application\/json persista en todos los requests del escenario"],"keyword":"*","line":7},{"name":"def val_fromAccountId = '13899'","result":{"duration":949600,"status":"passed"},"match":{"location":"karate","arguments":[]},"keyword":"*","line":8},{"name":"def val_toAccountId = '14565'","result":{"duration":583200,"status":"passed"},"match":{"location":"karate","arguments":[]},"keyword":"*","line":9},{"name":"def val_amount = 50","result":{"duration":672300,"status":"passed"},"match":{"location":"karate","arguments":[]},"keyword":"*","line":10}]},{"start_timestamp":"2026-05-21T00:59:15.937Z","line":12,"name":"Transferencia exitosa con validación de encadenamiento y libro mayor (ledger)","description":"","id":"transferencia-exitosa-con-validación-de-encadenamiento-y-libro-mayor-(ledger)","type":"scenario","keyword":"Scenario","steps":[{"name":"path 'transfer'","result":{"duration":360800,"status":"passed"},"match":{"location":"karate","arguments":[]},"comments":["# --- PASO 1: Ejecutar la transferencia ---"],"keyword":"Given","line":14},{"name":"param fromAccountId = val_fromAccountId","result":{"duration":462600,"status":"passed"},"match":{"location":"karate","arguments":[]},"keyword":"And","line":15},{"name":"param toAccountId = val_toAccountId","result":{"duration":370500,"status":"passed"},"match":{"location":"karate","arguments":[]},"keyword":"And","line":16},{"name":"param amount = val_amount","result":{"duration":399900,"status":"passed"},"match":{"location":"karate","arguments":[]},"keyword":"And","line":17},{"name":"method POST","result":{"duration":184571600,"status":"passed"},"match":{"location":"karate","arguments":[]},"keyword":"When","line":18,"doc_string":{"content_type":"","value":"19:59:15.945 request:\n1 > POST https:\/\/parabank.parasoft.com\/parabank\/services\/bank\/transfer?amount=50&fromAccountId=13899&toAccountId=14565\n1 > Accept: application\/json\n1 > Host: parabank.parasoft.com\n1 > Connection: Keep-Alive\n1 > User-Agent: Apache-HttpClient\/4.5.13 (Java\/21.0.7)\n1 > Accept-Encoding: gzip,deflate\n\n\n19:59:16.127 response time in milliseconds: 182\n1 < 200\n1 < Date: Thu, 21 May 2026 00:59:14 GMT\n1 < Content-Type: application\/json\n1 < Transfer-Encoding: chunked\n1 < Connection: keep-alive\n1 < Server: cloudflare\n1 < cf-cache-status: DYNAMIC\n1 < X-Content-Type-Options: nosniff\n1 < CF-RAY: 9fefa32988edb6ec-BOG\nSuccessfully transferred $50 from account #13899 to account #14565\n\n","line":18}},{"name":"status 200","result":{"duration":33000,"status":"passed"},"match":{"location":"karate","arguments":[]},"keyword":"Then","line":19},{"name":"def respuestaTransferencia = response","result":{"duration":211600,"status":"passed"},"match":{"location":"karate","arguments":[]},"keyword":"*","line":20},{"name":"path 'accounts', val_toAccountId, 'transactions'","result":{"duration":1038000,"status":"passed"},"match":{"location":"karate","arguments":[]},"comments":["# --- PASO 2: Encadenamiento - Verificación de Estado en el Libro Mayor ---","# GET automático al historial de la cuenta destino para validar la transacción"],"keyword":"Given","line":24},{"name":"method GET","result":{"duration":177895000,"status":"passed"},"match":{"location":"karate","arguments":[]},"keyword":"When","line":25,"doc_string":{"content_type":"","value":"19:59:16.131 request:\n2 > GET https:\/\/parabank.parasoft.com\/parabank\/services\/bank\/accounts\/14565\/transactions\n2 > Accept: application\/json\n2 > Host: parabank.parasoft.com\n2 > Connection: Keep-Alive\n2 > User-Agent: Apache-HttpClient\/4.5.13 (Java\/21.0.7)\n2 > Accept-Encoding: gzip,deflate\n\n\n19:59:16.307 response time in milliseconds: 175\n2 < 200\n2 < Date: Thu, 21 May 2026 00:59:15 GMT\n2 < Content-Type: application\/json\n2 < Transfer-Encoding: chunked\n2 < Connection: keep-alive\n2 < Server: cloudflare\n2 < cf-cache-status: DYNAMIC\n2 < X-Content-Type-Options: nosniff\n2 < CF-RAY: 9fefa32abfa5b6f6-BOG\n[{\"id\":16363,\"accountId\":14565,\"type\":\"Credit\",\"date\":1779321600000,\"amount\":90.00,\"description\":\"Funds Transfer Received\"},{\"id\":16585,\"accountId\":14565,\"type\":\"Credit\",\"date\":1779321600000,\"amount\":0.01,\"description\":\"Funds Transfer Received\"},{\"id\":18139,\"accountId\":14565,\"type\":\"Credit\",\"date\":1779321600000,\"amount\":50.00,\"description\":\"Funds Transfer Received\"},{\"id\":22357,\"accountId\":14565,\"type\":\"Credit\",\"date\":1779321600000,\"amount\":100.00,\"description\":\"Funds Transfer Received\"},{\"id\":22579,\"accountId\":14565,\"type\":\"Credit\",\"date\":1779321600000,\"amount\":100.00,\"description\":\"Funds Transfer Received\"},{\"id\":25687,\"accountId\":14565,\"type\":\"Credit\",\"date\":1779321600000,\"amount\":50.00,\"description\":\"Funds Transfer Received\"},{\"id\":26242,\"accountId\":14565,\"type\":\"Credit\",\"date\":1779321600000,\"amount\":50.00,\"description\":\"Funds Transfer Received\"},{\"id\":26908,\"accountId\":14565,\"type\":\"Credit\",\"date\":1779321600000,\"amount\":50.00,\"description\":\"Funds Transfer Received\"},{\"id\":27574,\"accountId\":14565,\"type\":\"Credit\",\"date\":1779321600000,\"amount\":50.00,\"description\":\"Funds Transfer Received\"},{\"id\":28240,\"accountId\":14565,\"type\":\"Credit\",\"date\":1779321600000,\"amount\":50.00,\"description\":\"Funds Transfer Received\"},{\"id\":29350,\"accountId\":14565,\"type\":\"Credit\",\"date\":1779321600000,\"amount\":50.00,\"description\":\"Funds Transfer Received\"},{\"id\":31459,\"accountId\":14565,\"type\":\"Credit\",\"date\":1779321600000,\"amount\":50.00,\"description\":\"Funds Transfer Received\"},{\"id\":32125,\"accountId\":14565,\"type\":\"Credit\",\"date\":1779321600000,\"amount\":50.00,\"description\":\"Funds Transfer Received\"},{\"id\":32791,\"accountId\":14565,\"type\":\"Credit\",\"date\":1779321600000,\"amount\":50.00,\"description\":\"Funds Transfer Received\"}]\n\n","line":25}},{"name":"status 200","result":{"duration":19100,"status":"passed"},"match":{"location":"karate","arguments":[]},"keyword":"Then","line":26},{"name":"def ultimaTransaccion = karate.jsonPath(response, '$[-1:]')[0]","result":{"duration":34967300,"status":"passed"},"match":{"location":"karate","arguments":[]},"comments":["# La API retorna transacciones en orden ascendente por ID (más antigua primero).","# Usamos JSONPath $[-1:] para obtener la más reciente de forma confiable."],"keyword":"*","line":30},{"name":"match ultimaTransaccion.type == 'Credit'","result":{"duration":2446400,"status":"passed"},"match":{"location":"karate","arguments":[]},"keyword":"*","line":31},{"name":"match ultimaTransaccion.amount == val_amount","result":{"duration":469800,"status":"passed"},"match":{"location":"karate","arguments":[]},"keyword":"*","line":32},{"result":{"duration":496500,"error_message":"match failed: EQUALS\n  $ | data types don't match (STRING:MAP)\n  'Successfully transferred $50 from account #13899 to account #14565'\n  {\"transactionId\":\"#number\"}\n\nclasspath:org\/udea\/parabank\/TransferFunds.feature:38","status":"failed"},"comments":["# --- DEFECTO DEL API (Criterio de Encadenamiento): ---","# El criterio exige que la respuesta del POST sea un objeto JSON con el ID de la transacción","# resultante, para permitir el encadenamiento directo via GET \/transactions\/{transactionId}.","# La API retorna texto plano sin ID, imposibilitando este encadenamiento según la especificación."],"line":38,"name":"match respuestaTransferencia == { \"transactionId\": '#number' }","match":{"location":"karate","arguments":[]},"keyword":"*","doc_string":{"content_type":"","value":"19:59:16.347 classpath:org\/udea\/parabank\/TransferFunds.feature:38\n* match respuestaTransferencia == { \"transactionId\": '#number' }\nmatch failed: EQUALS\n  $ | data types don't match (STRING:MAP)\n  'Successfully transferred $50 from account #13899 to account #14565'\n  {\"transactionId\":\"#number\"}\n\nclasspath:org\/udea\/parabank\/TransferFunds.feature:38\n","line":38}}],"tags":[{"name":"@parabank_transfer","line":1}]}],"name":"org\/udea\/parabank\/TransferFunds.feature","description":"Transferencia Atómica y Validación de Histórico","id":"transferencia-atómica-y-validación-de-histórico","keyword":"Feature","uri":"org\/udea\/parabank\/TransferFunds.feature","tags":[{"name":"@parabank_transfer","line":1}]}]